{
  "results": [
    {
      "schedule": "mixed029b_r32_a16",
      "min_final_majority_accuracy": 1.0,
      "min_final_consensus_accuracy": 0.0,
      "min_final_consensus_rate": 0.0,
      "min_checkerboard_2x2_fraction": 0.10931015014648438,
      "min_orthogonal_disagreement": 0.5384502410888672,
      "per_probability": [
        {
          "schedule": "mixed029b_r32_a16",
          "grid": "128x128",
          "trials": 32,
          "tied_initial_states": 0,
          "effective_trials": 32,
          "preprocess_steps": 128,
          "final_steps": 16,
          "local_majority_agreement": 0.5221195220947266,
          "local_density_variance": 0.02577291429042816,
          "preprocess_checkerboard_alignment": 0.007526397705078125,
          "preprocess_orthogonal_disagreement": 0.5384502410888672,
          "preprocess_checkerboard_2x2_fraction": 0.10931015014648438,
          "final_majority_accuracy": 1.0,
          "final_consensus_accuracy": 0.0,
          "final_consensus_rate": 0.0,
          "mean_final_density": 0.45606040954589844
        },
        {
          "schedule": "mixed029b_r32_a16",
          "grid": "128x128",
          "trials": 32,
          "tied_initial_states": 0,
          "effective_trials": 32,
          "preprocess_steps": 128,
          "final_steps": 16,
          "local_majority_agreement": 0.5256004333496094,
          "local_density_variance": 0.025647317990660667,
          "preprocess_checkerboard_alignment": 0.006839752197265625,
          "preprocess_orthogonal_disagreement": 0.5393695831298828,
          "preprocess_checkerboard_2x2_fraction": 0.11077690124511719,
          "final_majority_accuracy": 1.0,
          "final_consensus_accuracy": 0.0,
          "final_consensus_rate": 0.0,
          "mean_final_density": 0.5478992462158203
        }
      ]
    },
    {
      "schedule": "mixed029b_r40_a16",
      "min_final_majority_accuracy": 0.96875,
      "min_final_consensus_accuracy": 0.0,
      "min_final_consensus_rate": 0.0,
      "min_checkerboard_2x2_fraction": 0.10128974914550781,
      "min_orthogonal_disagreement": 0.5346622467041016,
      "per_probability": [
        {
          "schedule": "mixed029b_r40_a16",
          "grid": "128x128",
          "trials": 32,
          "tied_initial_states": 0,
          "effective_trials": 32,
          "preprocess_steps": 160,
          "final_steps": 16,
          "local_majority_agreement": 0.5218658447265625,
          "local_density_variance": 0.026489417999982834,
          "preprocess_checkerboard_alignment": 0.006656646728515625,
          "preprocess_orthogonal_disagreement": 0.5346622467041016,
          "preprocess_checkerboard_2x2_fraction": 0.10128974914550781,
          "final_majority_accuracy": 0.96875,
          "final_consensus_accuracy": 0.0,
          "final_consensus_rate": 0.0,
          "mean_final_density": 0.45378875732421875
        },
        {
          "schedule": "mixed029b_r40_a16",
          "grid": "128x128",
          "trials": 32,
          "tied_initial_states": 0,
          "effective_trials": 32,
          "preprocess_steps": 160,
          "final_steps": 16,
          "local_majority_agreement": 0.5253448486328125,
          "local_density_variance": 0.02639344334602356,
          "preprocess_checkerboard_alignment": 0.005153656005859375,
          "preprocess_orthogonal_disagreement": 0.5360851287841797,
          "preprocess_checkerboard_2x2_fraction": 0.10416221618652344,
          "final_majority_accuracy": 0.96875,
          "final_consensus_accuracy": 0.0,
          "final_consensus_rate": 0.0,
          "mean_final_density": 0.5475597381591797
        }
      ]
    },
    {
      "schedule": "mixed029b_r48_a16",
      "min_final_majority_accuracy": 0.9375,
      "min_final_consensus_accuracy": 0.0,
      "min_final_consensus_rate": 0.0,
      "min_checkerboard_2x2_fraction": 0.09614944458007812,
      "min_orthogonal_disagreement": 0.5318679809570312,
      "per_probability": [
        {
          "schedule": "mixed029b_r48_a16",
          "grid": "128x128",
          "trials": 32,
          "tied_initial_states": 0,
          "effective_trials": 32,
          "preprocess_steps": 192,
          "final_steps": 16,
          "local_majority_agreement": 0.5212001800537109,
          "local_density_variance": 0.02713838778436184,
          "preprocess_checkerboard_alignment": 0.005970001220703125,
          "preprocess_orthogonal_disagreement": 0.5318679809570312,
          "preprocess_checkerboard_2x2_fraction": 0.09614944458007812,
          "final_majority_accuracy": 0.9375,
          "final_consensus_accuracy": 0.0,
          "final_consensus_rate": 0.0,
          "mean_final_density": 0.45728492736816406
        },
        {
          "schedule": "mixed029b_r48_a16",
          "grid": "128x128",
          "trials": 32,
          "tied_initial_states": 0,
          "effective_trials": 32,
          "preprocess_steps": 192,
          "final_steps": 16,
          "local_majority_agreement": 0.5252132415771484,
          "local_density_variance": 0.026703327894210815,
          "preprocess_checkerboard_alignment": 0.006931304931640625,
          "preprocess_orthogonal_disagreement": 0.5341243743896484,
          "preprocess_checkerboard_2x2_fraction": 0.09977149963378906,
          "final_majority_accuracy": 1.0,
          "final_consensus_accuracy": 0.0,
          "final_consensus_rate": 0.0,
          "mean_final_density": 0.5503616333007812
        }
      ]
    },
    {
      "schedule": "mixed029b_r56_a16",
      "min_final_majority_accuracy": 0.96875,
      "min_final_consensus_accuracy": 0.0,
      "min_final_consensus_rate": 0.0,
      "min_checkerboard_2x2_fraction": 0.09195327758789062,
      "min_orthogonal_disagreement": 0.5294303894042969,
      "per_probability": [
        {
          "schedule": "mixed029b_r56_a16",
          "grid": "128x128",
          "trials": 32,
          "tied_initial_states": 0,
          "effective_trials": 32,
          "preprocess_steps": 224,
          "final_steps": 16,
          "local_majority_agreement": 0.5214004516601562,
          "local_density_variance": 0.027552682906389236,
          "preprocess_checkerboard_alignment": 0.005130767822265625,
          "preprocess_orthogonal_disagreement": 0.5294303894042969,
          "preprocess_checkerboard_2x2_fraction": 0.09195327758789062,
          "final_majority_accuracy": 0.96875,
          "final_consensus_accuracy": 0.0,
          "final_consensus_rate": 0.0,
          "mean_final_density": 0.4615345001220703
        },
        {
          "schedule": "mixed029b_r56_a16",
          "grid": "128x128",
          "trials": 32,
          "tied_initial_states": 0,
          "effective_trials": 32,
          "preprocess_steps": 224,
          "final_steps": 16,
          "local_majority_agreement": 0.5255050659179688,
          "local_density_variance": 0.027076557278633118,
          "preprocess_checkerboard_alignment": 0.006656646728515625,
          "preprocess_orthogonal_disagreement": 0.5321807861328125,
          "preprocess_checkerboard_2x2_fraction": 0.09570503234863281,
          "final_majority_accuracy": 1.0,
          "final_consensus_accuracy": 0.0,
          "final_consensus_rate": 0.0,
          "mean_final_density": 0.5485420227050781
        }
      ]
    },
    {
      "schedule": "mixed029b_r64_a16",
      "min_final_majority_accuracy": 1.0,
      "min_final_consensus_accuracy": 0.0,
      "min_final_consensus_rate": 0.0,
      "min_checkerboard_2x2_fraction": 0.08949661254882812,
      "min_orthogonal_disagreement": 0.5288124084472656,
      "per_probability": [
        {
          "schedule": "mixed029b_r64_a16",
          "grid": "128x128",
          "trials": 32,
          "tied_initial_states": 0,
          "effective_trials": 32,
          "preprocess_steps": 256,
          "final_steps": 16,
          "local_majority_agreement": 0.5210361480712891,
          "local_density_variance": 0.027710121124982834,
          "preprocess_checkerboard_alignment": 0.007907867431640625,
          "preprocess_orthogonal_disagreement": 0.5288333892822266,
          "preprocess_checkerboard_2x2_fraction": 0.08977508544921875,
          "final_majority_accuracy": 1.0,
          "final_consensus_accuracy": 0.0,
          "final_consensus_rate": 0.0,
          "mean_final_density": 0.4560585021972656
        },
        {
          "schedule": "mixed029b_r64_a16",
          "grid": "128x128",
          "trials": 32,
          "tied_initial_states": 0,
          "effective_trials": 32,
          "preprocess_steps": 256,
          "final_steps": 16,
          "local_majority_agreement": 0.5244235992431641,
          "local_density_variance": 0.027668118476867676,
          "preprocess_checkerboard_alignment": 0.005695343017578125,
          "preprocess_orthogonal_disagreement": 0.5288124084472656,
          "preprocess_checkerboard_2x2_fraction": 0.08949661254882812,
          "final_majority_accuracy": 1.0,
          "final_consensus_accuracy": 0.0,
          "final_consensus_rate": 0.0,
          "mean_final_density": 0.5517215728759766
        }
      ]
    }
  ]
}